pyamapping/__init__.py
pyamapping/mappings.py
pyamapping-0.1.0.dist-info/LICENSE.txt
pyamapping-0.1.0.dist-info/METADATA
pyamapping-0.1.0.dist-info/WHEEL
pyamapping-0.1.0.dist-info/top_level.txt
pyamapping-0.1.0.dist-info/RECORD
