Metadata-Version: 2.1
Name: pyamapping
Version: 0.1.0
Summary: A Python package containing audio related functions and mappings
Home-page: https://github.com/interactive-sonification/pyamapping
Author: Dennis Reinsch
Author-email: dreinsch@techfak.uni-bielefeld.de
License: MIT
Project-URL: Documentation, https://pyscaffold.org/
Platform: any
Classifier: Development Status :: 4 - Beta
Classifier: Programming Language :: Python
Provides-Extra: testing
License-File: LICENSE.txt
